{
  "regime": "risk-off",
  "risk_scale": 0.35,
  "avoid_symbols": [
    "MU",
    "SNDK",
    "NET",
    "META",
    "TSLA",
    "IRDM",
    "ANAB",
    "ETHUSD",
    "SOLUSD",
    "BRBR",
    "BWIN",
    "DTE",
    "VOD",
    "JXN"
  ],
  "favor_symbols": [
    "SPY",
    "QQQ"
  ],
  "notes": "Weekend brought a chip-led selloff (SK Hynix -10%, AI jitters), Iran saying Hormuz is closed with oil rising, and futures pointing lower into a CPI + Warsh testimony + bank-earnings week; VIX up to 16.5. Cutting to 0.35 and parking all semis/high-beta/crypto until the tape stabilizes.",
  "journal_entry": "Mon 7/13 09:00: dropped 0.5->0.35 and flipped risk-off. Weekend chip rout (SK Hynix -10%) plus Iran/Hormuz oil spike and CPI/Warsh this week broke Friday's calm; added MU/SNDK/META to avoids. Watching CPI print and whether semis stabilize before dialing back up.",
  "date": "2026-07-13",
  "mode": "MORNING",
  "updated_at": "2026-07-13T09:00 ET"
}