{
 "AAPL": {
  "basis": 322.125,
  "notional": 10.68,
  "peak": 330.605,
  "ts": "2026-07-13T09:45"
 },
 "ABT": {
  "basis": 98.99,
  "notional": 5.82,
  "peak": 100.64,
  "ts": "2026-07-16T12:45"
 },
 "META": {
  "basis": 649.1375,
  "notional": 38.09,
  "peak": 672.81,
  "peak_saved": 664.49,
  "ts": "2026-07-07T14:30"
 },
 "PLTK": {
  "basis": 4.155,
  "notional": 4.16,
  "ts": "2026-07-21T15:45"
 },
 "REZI": {
  "basis": 33.51,
  "notional": 18.75,
  "peak": 37.215,
  "peak_saved": 37.215,
  "ts": "2026-07-10T13:15"
 }
}